{
  "sprites": [
    {
      "fileName": "0.png",
      "width": 51,
      "height": 37,
      "x": 2,
      "y": 0
    },
    {
      "fileName": "1.png",
      "width": 51,
      "height": 37,
      "x": 54,
      "y": 0
    },
    {
      "fileName": "2.png",
      "width": 53,
      "height": 37,
      "x": 108,
      "y": 0
    },
    {
      "fileName": "3.png",
      "width": 53,
      "height": 37,
      "x": 162,
      "y": 0
    },
    {
      "fileName": "4.png",
      "width": 52,
      "height": 37,
      "x": 223,
      "y": 0
    },
    {
      "fileName": "5.png",
      "width": 52,
      "height": 37,
      "x": 276,
      "y": 0
    },
    {
      "fileName": "6.png",
      "width": 52,
      "height": 37,
      "x": 330,
      "y": 0
    },
    {
      "fileName": "7.png",
      "width": 52,
      "height": 37,
      "x": 384,
      "y": 0
    },
    {
      "fileName": "8.png",
      "width": 52,
      "height": 37,
      "x": 440,
      "y": 0
    },
    {
      "fileName": "9.png",
      "width": 52,
      "height": 37,
      "x": 494,
      "y": 0
    }
  ],
  "packMode": "grid",
  "padding": 0,
  "backgroundColor": "rgba(0, 0, 0, 0)",
  "spriteSheetWidth": 648,
  "spriteSheetHeight": 37
}